abml/.python-version
abml/__init__.py
abml/abml_analysis.py
abml/abml_assembly.py
abml/abml_bc.py
abml/abml_cae.py
abml/abml_constraint.py
abml/abml_contact_controls.py
abml/abml_helpers.py
abml/abml_interaction.py
abml/abml_interaction_property.py
abml/abml_loads.py
abml/abml_logger.py
abml/abml_materials.py
abml/abml_models.py
abml/abml_parts.py
abml/abml_region.py
abml/abml_sections.py
abml/abml_session.py
abml/abml_sketches.py
abml/abml_steps.py
abml-0.1.19.dist-info/METADATA
abml-0.1.19.dist-info/WHEEL
abml-0.1.19.dist-info/RECORD
