Metadata-Version: 2.1
Name: abml
Version: 0.1.19
Summary: 
Author: DavidNaizheZhou
Author-email: 70525024+DavidNaizheZhou@users.noreply.github.com
Requires-Python: >=2.7.15
Classifier: Programming Language :: Python :: 2
Classifier: Programming Language :: Python :: 3
Classifier: Programming Language :: Python :: 3.4
Classifier: Programming Language :: Python :: 3.5
Classifier: Programming Language :: Python :: 3.6
Classifier: Programming Language :: Python :: 3.7
Classifier: Programming Language :: Python :: 3.8
Classifier: Programming Language :: Python :: 3.9
Classifier: Programming Language :: Python :: 3.10
Classifier: Programming Language :: Python :: 3.11
Requires-Dist: pyaml (>=21.10.1,<22.0.0)
